twt_img/__init__.py
twt_img/exceptions.py
twt_img/twt_img.py
twitter_image_dl-0.2.2.dist-info/LICENSE
twitter_image_dl-0.2.2.dist-info/METADATA
twitter_image_dl-0.2.2.dist-info/WHEEL
twitter_image_dl-0.2.2.dist-info/entry_points.txt
twitter_image_dl-0.2.2.dist-info/top_level.txt
twitter_image_dl-0.2.2.dist-info/RECORD
