Metadata-Version: 2.1
Name: twitter-image-dl
Version: 0.2.2
Summary: Twitter image downloader
Home-page: https://github.com/morinokami/twitter-image-downloader
Author: Shinya Fujino
Author-email: shf0811@gmail.com
License: MIT
Keywords: Twitter,image
Platform: UNKNOWN
Classifier: Development Status :: 4 - Beta
Classifier: Environment :: Console
Classifier: License :: OSI Approved :: MIT License
Classifier: Programming Language :: Python :: 3
Classifier: Programming Language :: Python :: 3.6
Classifier: Programming Language :: Python :: 3.7
Classifier: Programming Language :: Python :: 3 :: Only
Classifier: Topic :: Multimedia :: Graphics
Requires-Dist: python-dateutil
Requires-Dist: requests
